[
    {
        "inputs": [
            {
                "internalType": "address",
                "name": "_governance",
                "type": "address"
            }
        ],
        "stateMutability": "nonpayable",
        "type": "constructor"
    },
    {
        "inputs": [
            {
                "internalType": "uint256",
                "name": "",
                "type": "uint256"
            }
        ],
        "name": "Domain_For_TXT",
        "outputs": [
            {
                "internalType": "string",
                "name": "",
                "type": "string"
            }
        ],
        "stateMutability": "view",
        "type": "function"
    },
    {
        "inputs": [
            {
                "internalType": "string",
                "name": "",
                "type": "string"
            }
        ],
        "name": "TXT_For_Domain",
        "outputs": [
            {
                "internalType": "uint256",
                "name": "",
                "type": "uint256"
            }
        ],
        "stateMutability": "view",
        "type": "function"
    },
    {
        "inputs": [
            {
                "internalType": "uint256",
                "name": "txt",
                "type": "uint256"
            }
        ],
        "name": "getDomainNameForTXT",
        "outputs": [
            {
                "internalType": "string",
                "name": "",
                "type": "string"
            }
        ],
        "stateMutability": "view",
        "type": "function"
    },
    {
        "inputs": [
            {
                "internalType": "string",
                "name": "domain",
                "type": "string"
            }
        ],
        "name": "getRandom",
        "outputs": [
            {
                "internalType": "bytes32",
                "name": "requestId",
                "type": "bytes32"
            }
        ],
        "stateMutability": "nonpayable",
        "type": "function"
    },
    {
        "inputs": [],
        "name": "governance",
        "outputs": [
            {
                "internalType": "contract governance_interface",
                "name": "",
                "type": "address"
            }
        ],
        "stateMutability": "view",
        "type": "function"
    },
    {
        "inputs": [
            {
                "internalType": "bytes32",
                "name": "",
                "type": "bytes32"
            }
        ],
        "name": "nonces",
        "outputs": [
            {
                "internalType": "uint256",
                "name": "",
                "type": "uint256"
            }
        ],
        "stateMutability": "view",
        "type": "function"
    },
    {
        "inputs": [
            {
                "internalType": "bytes32",
                "name": "requestId",
                "type": "bytes32"
            },
            {
                "internalType": "uint256",
                "name": "randomness",
                "type": "uint256"
            }
        ],
        "name": "rawFulfillRandomness",
        "outputs": [],
        "stateMutability": "nonpayable",
        "type": "function"
    },
    {
        "inputs": [],
        "name": "recentDomain",
        "outputs": [
            {
                "internalType": "string",
                "name": "",
                "type": "string"
            }
        ],
        "stateMutability": "view",
        "type": "function"
    },
    {
        "inputs": [],
        "name": "recentRequestId",
        "outputs": [
            {
                "internalType": "bytes32",
                "name": "",
                "type": "bytes32"
            }
        ],
        "stateMutability": "view",
        "type": "function"
    },
    {
        "inputs": [],
        "name": "recentTXT",
        "outputs": [
            {
                "internalType": "uint256",
                "name": "",
                "type": "uint256"
            }
        ],
        "stateMutability": "view",
        "type": "function"
    },
    {
        "inputs": [
            {
                "internalType": "bytes32",
                "name": "",
                "type": "bytes32"
            }
        ],
        "name": "requestIds",
        "outputs": [
            {
                "internalType": "string",
                "name": "",
                "type": "string"
            }
        ],
        "stateMutability": "view",
        "type": "function"
    },
    {
        "inputs": [
            {
                "internalType": "bytes32",
                "name": "_keyHash",
                "type": "bytes32"
            },
            {
                "internalType": "uint256",
                "name": "_fee",
                "type": "uint256"
            },
            {
                "internalType": "uint256",
                "name": "_seed",
                "type": "uint256"
            }
        ],
        "name": "requestRandomness",
        "outputs": [
            {
                "internalType": "bytes32",
                "name": "requestId",
                "type": "bytes32"
            }
        ],
        "stateMutability": "nonpayable",
        "type": "function"
    }
]